pylib_0xe/README.md
pylib_0xe/__init__.py
pylib_0xe/py.typed
pylib_0xe/argument/argument_parser.py
pylib_0xe/asynchrone/async_helper.py
pylib_0xe/asynchrone/get_lock.py
pylib_0xe/asynchrone/get_or_create_event_loop.py
pylib_0xe/buffer_io/buffer.py
pylib_0xe/buffer_io/buffer_reader.py
pylib_0xe/buffer_io/buffer_writer.py
pylib_0xe/buffer_io/file_buffer.py
pylib_0xe/buffer_io/standard_input_buffer.py
pylib_0xe/buffer_io/standard_output_buffer.py
pylib_0xe/buffer_io/string_buffer.py
pylib_0xe/buffer_io/helpers/character_detector.py
pylib_0xe/buffer_io/helpers/character_types.py
pylib_0xe/config/config.py
pylib_0xe/data/data_transfer_object.py
pylib_0xe/data/variable_type_modifier.py
pylib_0xe/data_structures/graph/graph.py
pylib_0xe/data_structures/trees/avl_tree/avl_node.py
pylib_0xe/data_structures/trees/avl_tree/avl_tree.py
pylib_0xe/data_structures/trees/avl_tree/merge_avl_trees.py
pylib_0xe/data_structures/trees/bk_tree/bk_node.py
pylib_0xe/data_structures/trees/bk_tree/bk_tree.py
pylib_0xe/data_structures/trees/fenwick_tree/fenwick_tree.py
pylib_0xe/data_structures/trees/trie_tree/trie_node.py
pylib_0xe/data_structures/trees/trie_tree/trie_tree.py
pylib_0xe/database/decorated_base.py
pylib_0xe/database/paginate_reader.py
pylib_0xe/database/session_pools.py
pylib_0xe/database/actions/borrow_session.py
pylib_0xe/database/actions/cleanup_sessions.py
pylib_0xe/database/actions/create_database_session.py
pylib_0xe/database/actions/release_session.py
pylib_0xe/database/engines/postgres_engine.py
pylib_0xe/database/infos/database_info.py
pylib_0xe/database/infos/postgres_database_info.py
pylib_0xe/database/mediators/engine_mediator.py
pylib_0xe/database/mediators/session_mediator.py
pylib_0xe/decorators/async_time_cheker.py
pylib_0xe/decorators/db_session.py
pylib_0xe/decorators/inject_async_connection.py
pylib_0xe/decorators/inject_blocking_connection.py
pylib_0xe/decorators/reconnect_wrapper.py
pylib_0xe/decorators/singleton.py
pylib_0xe/decorators/thread_lock.py
pylib_0xe-0.1.3.dist-info/LICENSE
pylib_0xe-0.1.3.dist-info/METADATA
pylib_0xe-0.1.3.dist-info/WHEEL
pylib_0xe-0.1.3.dist-info/top_level.txt
pylib_0xe-0.1.3.dist-info/RECORD
