Metadata-Version: 2.1
Name: pylib-0xe
Version: 0.1.3
Summary: Yet Another Python Library
Author-email: shamir0xe <shamir0xe@gmail.com>
License: The MIT License (MIT)
Project-URL: Homepage, https://github.com/shamir0xe/pylib
Keywords: library,asynchrone,database,messaging,reader,writer,data structures,config reader,json reader,json writer,json,repository,geometry,math,decorators
Classifier: License :: OSI Approved :: MIT License
Classifier: Programming Language :: Python
Classifier: Programming Language :: Python :: 3
Classifier: Operating System :: OS Independent
Requires-Python: >=3.12.3
License-File: LICENSE
Requires-Dist: annotated-types==0.7.0
Requires-Dist: greenlet==3.1.1
Requires-Dist: pika==1.3.2
Requires-Dist: pydantic==2.10.3
Requires-Dist: pydantic_core==2.27.1
Requires-Dist: python-ulid==3.0.0
Requires-Dist: SQLAlchemy==2.0.36
Requires-Dist: typing_extensions==4.12.2
Provides-Extra: dev
Requires-Dist: unittest; extra == "dev"
